cadence/__init__.py
cadence/__main__.py
cadence/cadence.py
cadence/cli.py
cadence/diagram.py
cadence/exceptions.py
cadence/hooks.py
cadence/note.py
cadence/py.typed
cadence/result.py
cadence/score.py
cadence/types.py
cadence/integrations/__init__.py
cadence/integrations/fastapi.py
cadence/integrations/flask.py
cadence/nodes/__init__.py
cadence/nodes/base.py
cadence/nodes/branch.py
cadence/nodes/child.py
cadence/nodes/parallel.py
cadence/nodes/sequence.py
cadence/nodes/single.py
cadence/reporters/__init__.py
cadence/reporters/console.py
cadence/reporters/opentelemetry.py
cadence/reporters/prometheus.py
cadence/resilience/__init__.py
cadence/resilience/circuit_breaker.py
cadence/resilience/fallback.py
cadence/resilience/retry.py
cadence/resilience/timeout.py
cadence_orchestration-0.4.2.dist-info/METADATA
cadence_orchestration-0.4.2.dist-info/WHEEL
cadence_orchestration-0.4.2.dist-info/entry_points.txt
cadence_orchestration-0.4.2.dist-info/licenses/LICENSE
cadence_orchestration-0.4.2.dist-info/RECORD
