Metadata-Version: 2.4
Name: cadence-orchestration
Version: 0.4.2
Summary: A declarative Python framework for orchestrating service logic with rhythm and precision
Project-URL: Homepage, https://github.com/mauhpr/cadence
Project-URL: Documentation, https://github.com/mauhpr/cadence#readme
Project-URL: Repository, https://github.com/mauhpr/cadence
Project-URL: Issues, https://github.com/mauhpr/cadence/issues
Author: Mauricio Perez Romero
License-Expression: MIT
License-File: LICENSE
Keywords: api,async,cadence,circuit-breaker,declarative,dsl,orchestration,pipeline,resilience,service,workflow
Classifier: Development Status :: 4 - Beta
Classifier: Framework :: AsyncIO
Classifier: Framework :: FastAPI
Classifier: Framework :: Flask
Classifier: Intended Audience :: Developers
Classifier: License :: OSI Approved :: MIT License
Classifier: Operating System :: OS Independent
Classifier: Programming Language :: Python :: 3
Classifier: Programming Language :: Python :: 3.10
Classifier: Programming Language :: Python :: 3.11
Classifier: Programming Language :: Python :: 3.12
Classifier: Programming Language :: Python :: 3.13
Classifier: Topic :: Software Development :: Libraries :: Python Modules
Classifier: Typing :: Typed
Requires-Python: >=3.10
Provides-Extra: all
Requires-Dist: fastapi>=0.128.0; extra == 'all'
Requires-Dist: flask>=3.1.2; extra == 'all'
Requires-Dist: graphviz>=0.21; extra == 'all'
Requires-Dist: opentelemetry-api>=1.39.1; extra == 'all'
Requires-Dist: opentelemetry-sdk>=1.39.1; extra == 'all'
Requires-Dist: prometheus-client>=0.23.1; extra == 'all'
Requires-Dist: starlette>=0.50.0; extra == 'all'
Provides-Extra: dev
Requires-Dist: mypy>=1.19.1; extra == 'dev'
Requires-Dist: pytest-asyncio>=1.3.0; extra == 'dev'
Requires-Dist: pytest-cov>=7.0.0; extra == 'dev'
Requires-Dist: pytest>=9.0.2; extra == 'dev'
Requires-Dist: ruff>=0.14.11; extra == 'dev'
Provides-Extra: diagram
Requires-Dist: graphviz>=0.21; extra == 'diagram'
Provides-Extra: fastapi
Requires-Dist: fastapi>=0.128.0; extra == 'fastapi'
Requires-Dist: starlette>=0.50.0; extra == 'fastapi'
Provides-Extra: flask
Requires-Dist: flask>=3.1.2; extra == 'flask'
Provides-Extra: opentelemetry
Requires-Dist: opentelemetry-api>=1.39.1; extra == 'opentelemetry'
Requires-Dist: opentelemetry-sdk>=1.39.1; extra == 'opentelemetry'
Provides-Extra: prometheus
Requires-Dist: prometheus-client>=0.23.1; extra == 'prometheus'
